{ "height":15,
 "layers":[
        {
         "data":[120, 120, 120, 73, 75, 120, 120, 120, 120, 120, 107, 120, 89, 84, 1, 1, 1, 1, 1, 119, 73, 74, 75, 81, 83, 120, 120, 73, 97, 75, 120, 120, 120, 89, 84, 1, 1, 1, 1, 122, 81, 1, 77, 76, 77, 74, 74, 76, 1, 77, 75, 73, 74, 75, 89, 84, 1, 1, 1, 1, 89, 84, 1, 1, 1, 1, 1, 1, 1, 1, 1, 1, 1, 1, 93, 1, 1, 1, 1, 85, 73, 76, 1, 85, 84, 1, 85, 84, 1, 85, 91, 89, 90, 91, 120, 89, 84, 1, 85, 91, 89, 90, 104, 91, 89, 90, 91, 89, 103, 91, 120, 120, 120, 73, 74, 75, 89, 104, 91, 120, 120, 73, 1, 74, 74, 74, 75, 73, 1, 75, 120, 120, 120, 81, 1, 77, 74, 1, 75, 120, 120, 81, 1, 1, 1, 1, 77, 76, 1, 83, 120, 120, 120, 89, 84, 1, 1, 1, 83, 120, 120, 89, 104, 104, 84, 1, 1, 1, 1, 83, 120, 120, 120, 120, 89, 90, 104, 90, 91, 120, 99, 120, 104, 103, 89, 90, 84, 1, 85, 91, 120, 120, 120, 120, 120, 73, 1, 74, 75, 120, 120, 120, 120, 104, 120, 120, 89, 98, 91, 120, 120, 120, 99, 120, 120, 81, 1, 1, 83, 120, 73, 74, 1, 1, 97, 75, 120, 120, 120, 120, 120, 120, 120, 107, 73, 76, 1, 85, 91, 120, 81, 1, 1, 1, 1, 83, 120, 120, 120, 120, 120, 120, 120, 120, 81, 1, 1, 83, 120, 120, 81, 1, 1, 1, 1, 83, 120, 120, 120, 120, 120, 120, 120, 120, 89, 90, 90, 91, 120, 120, 89, 90, 98, 90, 90, 91, 120, 120, 120, 120, 120, 120, 120, 120, 120, 120, 120, 120, 120, 120],
         "height":15,
         "name":"1",
         "opacity":1,
         "type":"tilelayer",
         "visible":true,
         "width":20,
         "x":0,
         "y":0
        }, 
        {
         "data":[0, 0, 0, 0, 61, 62, 63, 64, 0, 0, 0, 0, 0, 0, 12, 24, 65, 78, 79, 0, 0, 0, 0, 0, 69, 70, 71, 72, 0, 0, 0, 28, 29, 0, 0, 32, 21, 0, 8, 0, 0, 7, 0, 0, 0, 0, 0, 0, 22, 0, 0, 0, 0, 0, 0, 0, 0, 23, 0, 11, 0, 0, 0, 0, 0, 0, 0, 0, 0, 0, 86, 88, 0, 86, 0, 88, 0, 31, 0, 0, 0, 0, 96, 0, 0, 11, 0, 0, 96, 0, 0, 0, 0, 0, 0, 0, 0, 96, 0, 37, 0, 0, 0, 0, 0, 0, 0, 0, 0, 0, 0, 0, 0, 0, 0, 0, 0, 0, 0, 0, 0, 0, 112, 0, 0, 0, 0, 0, 112, 0, 0, 0, 0, 0, 13, 0, 0, 112, 0, 0, 0, 0, 96, 96, 7, 0, 0, 0, 0, 0, 0, 0, 0, 0, 0, 0, 96, 0, 0, 0, 0, 0, 0, 0, 0, 30, 0, 23, 0, 0, 0, 17, 18, 0, 0, 0, 0, 0, 0, 0, 0, 0, 0, 0, 0, 38, 0, 31, 0, 0, 0, 0, 0, 0, 0, 0, 112, 0, 0, 0, 0, 0, 94, 0, 0, 0, 0, 0, 0, 0, 0, 0, 0, 0, 0, 0, 0, 8, 0, 0, 0, 0, 112, 112, 0, 0, 0, 0, 0, 0, 0, 0, 0, 0, 0, 0, 0, 0, 0, 0, 0, 19, 0, 0, 0, 0, 0, 0, 0, 0, 15, 0, 0, 0, 0, 10, 0, 0, 30, 0, 0, 0, 0, 0, 7, 0, 0, 0, 16, 0, 0, 0, 0, 0, 0, 0, 0, 0, 38, 0, 0, 0, 0, 0, 0, 0, 0, 0, 0, 0, 0, 0, 0, 0, 0, 0, 0, 0, 0, 0],
         "height":15,
         "name":"2",
         "opacity":1,
         "type":"tilelayer",
         "visible":true,
         "width":20,
         "x":0,
         "y":0
        }, 
        {
         "data":[0, 0, 0, 0, 0, 0, 0, 0, 0, 0, 0, 0, 0, 0, 0, 0, 0, 0, 0, 0, 0, 0, 0, 0, 0, 0, 0, 0, 0, 0, 0, 0, 0, 0, 0, 0, 0, 0, 0, 0, 0, 0, 0, 0, 0, 0, 0, 0, 0, 0, 0, 0, 0, 0, 0, 0, 0, 0, 0, 0, 0, 0, 0, 0, 0, 0, 0, 0, 0, 45, 46, 47, 48, 0, 0, 0, 0, 0, 0, 0, 0, 0, 0, 0, 0, 0, 0, 0, 0, 53, 54, 55, 56, 0, 0, 0, 0, 0, 0, 0, 0, 0, 0, 0, 0, 0, 0, 0, 0, 61, 62, 63, 64, 0, 0, 0, 0, 0, 0, 0, 0, 0, 0, 0, 0, 0, 0, 0, 0, 69, 70, 71, 72, 0, 0, 0, 0, 0, 0, 0, 0, 0, 0, 0, 0, 0, 0, 0, 0, 0, 0, 0, 0, 0, 0, 0, 0, 0, 0, 0, 0, 0, 0, 0, 0, 0, 0, 0, 0, 0, 0, 0, 0, 0, 0, 0, 0, 0, 0, 0, 0, 0, 0, 0, 0, 45, 46, 47, 48, 0, 0, 0, 0, 0, 0, 0, 0, 0, 0, 0, 0, 0, 0, 0, 0, 53, 54, 55, 56, 0, 0, 0, 0, 0, 0, 0, 0, 0, 0, 0, 0, 0, 0, 0, 0, 61, 62, 63, 64, 0, 0, 0, 0, 0, 0, 0, 0, 0, 0, 0, 0, 0, 0, 0, 0, 69, 70, 71, 72, 0, 0, 0, 0, 0, 0, 0, 0, 0, 0, 0, 0, 0, 0, 0, 0, 0, 0, 0, 0, 0, 0, 0, 0, 0, 0, 0, 0, 0, 0, 0, 0, 0, 0, 0, 0, 0, 0, 0, 0, 0, 0, 0, 0, 0, 0, 0, 0, 0, 0, 0],
         "height":15,
         "name":"3",
         "opacity":1,
         "type":"tilelayer",
         "visible":true,
         "width":20,
         "x":0,
         "y":0
        }, 
        {
         "height":15,
         "name":"events",
         "objects":[
                {
                 "height":32,
                 "name":"warp_map3",
                 "properties":
                    {
                     "file":"warp_map3"
                    },
                 "type":"event",
                 "visible":true,
                 "width":32,
                 "x":512,
                 "y":0
                }],
         "opacity":1,
         "type":"objectgroup",
         "visible":true,
         "width":20,
         "x":0,
         "y":0
        }],
 "orientation":"orthogonal",
 "properties":
    {
     "name":"map1"
    },
 "tileheight":32,
 "tilesets":[
        {
         "firstgid":1,
         "image":"swamp.png",
         "imageheight":448,
         "imagewidth":256,
         "margin":0,
         "name":"swamp",
         "properties":
            {

            },
         "spacing":0,
         "tileheight":32,
         "tileproperties":
            {
             "0":
                {
                 "layer":"0",
                 "passable":"1"
                },
             "1":
                {
                 "layer":"0",
                 "passable":"1"
                },
             "10":
                {
                 "layer":"0",
                 "passable":"0"
                },
             "100":
                {
                 "layer":"0"
                },
             "101":
                {
                 "layer":"0"
                },
             "102":
                {
                 "layer":"0"
                },
             "103":
                {
                 "layer":"0"
                },
             "104":
                {
                 "layer":"0",
                 "passable":"0"
                },
             "105":
                {
                 "layer":"0",
                 "passable":"0"
                },
             "106":
                {
                 "layer":"0",
                 "passable":"0"
                },
             "107":
                {
                 "layer":"0",
                 "passable":"0"
                },
             "108":
                {
                 "layer":"0",
                 "passable":"0"
                },
             "109":
                {
                 "layer":"0",
                 "passable":"0"
                },
             "11":
                {
                 "layer":"0",
                 "passable":"0"
                },
             "110":
                {
                 "layer":"0",
                 "passable":"0"
                },
             "111":
                {
                 "layer":"0"
                },
             "12":
                {
                 "layer":"0",
                 "passable":"0"
                },
             "13":
                {
                 "layer":"0",
                 "passable":"0"
                },
             "14":
                {
                 "layer":"0"
                },
             "15":
                {
                 "layer":"0"
                },
             "16":
                {
                 "layer":"0",
                 "passable":"0"
                },
             "17":
                {
                 "layer":"0",
                 "passable":"0"
                },
             "18":
                {
                 "layer":"0",
                 "passable":"0"
                },
             "19":
                {
                 "layer":"0",
                 "passable":"0"
                },
             "2":
                {
                 "layer":"0",
                 "passable":"1"
                },
             "20":
                {
                 "layer":"0"
                },
             "21":
                {
                 "layer":"0"
                },
             "22":
                {
                 "layer":"0"
                },
             "23":
                {
                 "layer":"0",
                 "passable":"0"
                },
             "24":
                {
                 "layer":"0",
                 "passable":"0"
                },
             "25":
                {
                 "layer":"0",
                 "passable":"0"
                },
             "26":
                {
                 "layer":"0",
                 "passable":"0"
                },
             "27":
                {
                 "layer":"0",
                 "passable":"0"
                },
             "28":
                {
                 "layer":"0",
                 "passable":"0"
                },
             "29":
                {
                 "layer":"1"
                },
             "3":
                {
                 "layer":"0",
                 "passable":"1"
                },
             "30":
                {
                 "layer":"0"
                },
             "31":
                {
                 "layer":"0",
                 "passable":"0"
                },
             "32":
                {
                 "layer":"0",
                 "passable":"0"
                },
             "33":
                {
                 "layer":"0",
                 "passable":"0"
                },
             "34":
                {
                 "layer":"0",
                 "passable":"0"
                },
             "36":
                {
                 "layer":"0",
                 "passable":"0"
                },
             "37":
                {
                 "layer":"0",
                 "passable":"0"
                },
             "38":
                {
                 "layer":"0",
                 "passable":"0"
                },
             "39":
                {
                 "layer":"0",
                 "passable":"0"
                },
             "4":
                {
                 "layer":"0"
                },
             "40":
                {
                 "layer":"1"
                },
             "41":
                {
                 "layer":"1"
                },
             "42":
                {
                 "layer":"1"
                },
             "43":
                {
                 "layer":"1"
                },
             "44":
                {
                 "layer":"1"
                },
             "45":
                {
                 "layer":"1"
                },
             "46":
                {
                 "layer":"1"
                },
             "48":
                {
                 "layer":"1"
                },
             "49":
                {
                 "layer":"1"
                },
             "5":
                {
                 "layer":"0"
                },
             "50":
                {
                 "layer":"1"
                },
             "51":
                {
                 "layer":"1"
                },
             "52":
                {
                 "layer":"1"
                },
             "53":
                {
                 "layer":"1"
                },
             "54":
                {
                 "layer":"1"
                },
             "55":
                {
                 "layer":"1"
                },
             "56":
                {
                 "layer":"1"
                },
             "57":
                {
                 "layer":"1"
                },
             "58":
                {
                 "layer":"1"
                },
             "59":
                {
                 "layer":"1"
                },
             "6":
                {
                 "layer":"0"
                },
             "60":
                {
                 "layer":"1"
                },
             "61":
                {
                 "layer":"1"
                },
             "62":
                {
                 "layer":"1"
                },
             "63":
                {
                 "layer":"1"
                },
             "64":
                {
                 "layer":"0"
                },
             "65":
                {
                 "layer":"0",
                 "passable":"0"
                },
             "66":
                {
                 "layer":"0",
                 "passable":"0"
                },
             "67":
                {
                 "layer":"0"
                },
             "68":
                {
                 "layer":"0"
                },
             "69":
                {
                 "layer":"0",
                 "passable":"0"
                },
             "7":
                {
                 "layer":"0"
                },
             "70":
                {
                 "layer":"0",
                 "passable":"0"
                },
             "71":
                {
                 "layer":"0"
                },
             "72":
                {
                 "layer":"0",
                 "passable":"0"
                },
             "73":
                {
                 "layer":"0",
                 "passable":"0"
                },
             "74":
                {
                 "layer":"0",
                 "passable":"0"
                },
             "75":
                {
                 "layer":"0",
                 "passable":"0"
                },
             "76":
                {
                 "layer":"0",
                 "passable":"0"
                },
             "77":
                {
                 "layer":"0",
                 "passable":"0"
                },
             "78":
                {
                 "layer":"0",
                 "passable":"0"
                },
             "8":
                {
                 "layer":"0",
                 "passable":"0"
                },
             "80":
                {
                 "layer":"0",
                 "passable":"0"
                },
             "81":
                {
                 "layer":"0",
                 "passable":"0"
                },
             "82":
                {
                 "layer":"0",
                 "passable":"0"
                },
             "83":
                {
                 "layer":"0",
                 "passable":"0"
                },
             "84":
                {
                 "layer":"0",
                 "passable":"0"
                },
             "85":
                {
                 "layer":"0"
                },
             "86":
                {
                 "layer":"0"
                },
             "87":
                {
                 "layer":"0"
                },
             "88":
                {
                 "layer":"0",
                 "passable":"0"
                },
             "89":
                {
                 "layer":"0",
                 "passable":"0"
                },
             "9":
                {
                 "layer":"0",
                 "passable":"0"
                },
             "90":
                {
                 "layer":"0",
                 "passable":"0"
                },
             "91":
                {
                 "layer":"0",
                 "passable":"0"
                },
             "92":
                {
                 "layer":"0"
                },
             "93":
                {
                 "layer":"0",
                 "passable":"0"
                },
             "94":
                {
                 "layer":"0",
                 "passable":"0"
                },
             "95":
                {
                 "layer":"0"
                },
             "96":
                {
                 "layer":"0",
                 "passable":"0"
                },
             "97":
                {
                 "layer":"0",
                 "passable":"0"
                },
             "98":
                {
                 "layer":"0",
                 "passable":"0"
                }
            },
         "tilewidth":32
        }, 
        {
         "firstgid":113,
         "image":"swamp2.png",
         "imageheight":128,
         "imagewidth":96,
         "margin":0,
         "name":"swamp2",
         "properties":
            {

            },
         "spacing":0,
         "tileheight":32,
         "tileproperties":
            {
             "0":
                {
                 "layer":"0",
                 "passable":"0"
                },
             "1":
                {
                 "layer":"0"
                },
             "10":
                {
                 "layer":"0",
                 "passable":"0"
                },
             "11":
                {
                 "layer":"0",
                 "passable":"0"
                },
             "2":
                {
                 "layer":"0",
                 "passable":"0"
                },
             "3":
                {
                 "layer":"0",
                 "passable":"0"
                },
             "4":
                {
                 "layer":"0",
                 "passable":"0"
                },
             "5":
                {
                 "layer":"0",
                 "passable":"0"
                },
             "6":
                {
                 "layer":"0",
                 "passable":"0"
                },
             "7":
                {
                 "layer":"0",
                 "passable":"0"
                },
             "8":
                {
                 "layer":"0",
                 "passable":"0"
                },
             "9":
                {
                 "layer":"0",
                 "passable":"0"
                }
            },
         "tilewidth":32
        }],
 "tilewidth":32,
 "version":1,
 "width":20
}